dorkas/__init__.py
dorkas/q1.py
dorkas-0.1.3.dist-info/METADATA
dorkas-0.1.3.dist-info/WHEEL
dorkas-0.1.3.dist-info/licenses/LICENSE
dorkas-0.1.3.dist-info/RECORD
